{"information": "annualBalanceF0503721", "annualBalance": {"hasViolationsProtocol": false, "modifyDate": 1458121524748, "founder": null, "lockVersion": 17, "founderAuthorityName": "\u0414\u0415\u041f\u0410\u0420\u0422\u0410\u041c\u0415\u041d\u0422 \u041e\u0411\u0420\u0410\u0417\u041e\u0412\u0410\u041d\u0418\u042f \u0413\u041e\u0420\u041e\u0414\u0410 \u041c\u041e\u0421\u041a\u0412\u042b", "oktmo": null, "id": 461757, "checkedByFounder": null, "founderAgencyId": 205363, "publishedBy": null, "agencyId": 158081, "okei": {"lastModifyDate": null, "actual": true, "charCode": "\u0420\u0423\u0411", "entityClass": "ru.lanit.gmu.priv.model.nsi.Okei", "name": "\u0420\u0443\u0431\u043b\u044c", "gmuOkeiCode": "1000227", "section": null, "group": null, "activeFromDate": null, "activeToDate": null, "internationName": null, "hibernateLazyInitializer": {}, "localName": "\u0440\u0443\u0431", "internationCharCode": null, "digitalCode": "383", "id": 202301}, "section": null, "formationPeriod": 2015, "separateStructuralUnitName": null, "version": 0, "separateStructuralUnitOkpoCode": null, "printForm": null, "sid": 461757, "incomings": [{"stateAgencyBalance": null, "budgetActivityEndYear": "6,206,377.80", "totalEndYear": "400,814,704.06", "budgetActivityBeginYear": "6,206,377.80", "entityClass": "ru.lanit.gmu.priv.model.document.BalanceItem", "name": "\u0414\u043e\u0445\u043e\u0434\u044b (\u0441\u0442\u0440. 030 + \u0441\u0442\u0440. 040 + \u0441\u0442\u0440. 050 + \u0441\u0442\u0440. 060 + \u0441\u0442\u0440. 090 + \u0441\u0442\u0440. 100 + \u0441\u0442\u0440. 110 )", "totalBeginYear": "400,814,704.06", "incomeActivityEndYear": "370,673,492.84", "availableMeansBeginYear": "23,934,833.42", "lineCode": "010", "incomeActivityBeginYear": "370,673,492.84", "position": 0, "availableMeansEndYear": "23,934,833.42", "id": 59409620, "sectionNumber": "100"}, {"stateAgencyBalance": null, "budgetActivityEndYear": null, "totalEndYear": null, "budgetActivityBeginYear": null, "entityClass": "ru.lanit.gmu.priv.model.document.BalanceItem", "name": "\u0414\u043e\u0445\u043e\u0434\u044b \u043e\u0442 \u0441\u043e\u0431\u0441\u0442\u0432\u0435\u043d\u043d\u043e\u0441\u0442\u0438", "totalBeginYear": null, "incomeActivityEndYear": null, "availableMeansBeginYear": null, "lineCode": "030", "incomeActivityBeginYear": null, "position": 0, "availableMeansEndYear": null, "id": 59409621, "sectionNumber": "120"}, {"stateAgencyBalance": null, "budgetActivityEndYear": null, "totalEndYear": "23,334,759.01", "budgetActivityBeginYear": null, "entityClass": "ru.lanit.gmu.priv.model.document.BalanceItem", "name": "\u0414\u043e\u0445\u043e\u0434\u044b \u043e\u0442 \u043e\u043a\u0430\u0437\u0430\u043d\u0438\u044f \u043f\u043b\u0430\u0442\u043d\u044b\u0445 \u0443\u0441\u043b\u0443\u0433 (\u0440\u0430\u0431\u043e\u0442)", "totalBeginYear": "23,334,759.01", "incomeActivityEndYear": null, "availableMeansBeginYear": "23,334,759.01", "lineCode": "040", "incomeActivityBeginYear": null, "position": 0, "availableMeansEndYear": "23,334,759.01", "id": 59409622, "sectionNumber": "130"}, {"stateAgencyBalance": null, "budgetActivityEndYear": null, "totalEndYear": null, "budgetActivityBeginYear": null, "entityClass": "ru.lanit.gmu.priv.model.document.BalanceItem", "name": "\u0414\u043e\u0445\u043e\u0434\u044b \u043e\u0442 \u0448\u0442\u0440\u0430\u0444\u043e\u0432, \u043f\u0435\u043d\u0438, \u0438\u043d\u044b\u0445 \u0441\u0443\u043c\u043c \u043f\u0440\u0438\u043d\u0443\u0434\u0438\u0442\u0435\u043b\u044c\u043d\u043e\u0433\u043e \u0438\u0437\u044a\u044f\u0442\u0438\u044f", "totalBeginYear": null, "incomeActivityEndYear": null, "availableMeansBeginYear": null, "lineCode": "050", "incomeActivityBeginYear": null, "position": 0, "availableMeansEndYear": null, "id": 59409623, "sectionNumber": "140"}, {"stateAgencyBalance": null, "budgetActivityEndYear": null, "totalEndYear": null, "budgetActivityBeginYear": null, "entityClass": "ru.lanit.gmu.priv.model.document.BalanceItem", "name": "\u0411\u0435\u0437\u0432\u043e\u0437\u043c\u0435\u0437\u0434\u043d\u044b\u0435 \u043f\u043e\u0441\u0442\u0443\u043f\u043b\u0435\u043d\u0438\u044f \u043e\u0442 \u0431\u044e\u0434\u0436\u0435\u0442\u043e\u0432", "totalBeginYear": null, "incomeActivityEndYear": null, "availableMeansBeginYear": null, "lineCode": "060", "incomeActivityBeginYear": null, "position": 0, "availableMeansEndYear": null, "id": 59409624, "sectionNumber": "150"}, {"stateAgencyBalance": null, "budgetActivityEndYear": null, "totalEndYear": null, "budgetActivityBeginYear": null, "entityClass": "ru.lanit.gmu.priv.model.document.BalanceItem", "name": "\u043f\u043e\u0441\u0442\u0443\u043f\u043b\u0435\u043d\u0438\u044f \u043e\u0442 \u043d\u0430\u0434\u043d\u0430\u0446\u0438\u043e\u043d\u0430\u043b\u044c\u043d\u044b\u0445 \u043e\u0440\u0433\u0430\u043d\u0438\u0437\u0430\u0446\u0438\u0439 \u0438 \u043f\u0440\u0430\u0432\u0438\u0442\u0435\u043b\u044c\u0441\u0442\u0432 \u0438\u043d\u043e\u0441\u0442\u0440\u0430\u043d\u043d\u044b\u0445 \u0433\u043e\u0441\u0443\u0434\u0430\u0440\u0441\u0442\u0432 ", "totalBeginYear": null, "incomeActivityEndYear": null, "availableMeansBeginYear": null, "lineCode": "062", "incomeActivityBeginYear": null, "position": 0, "availableMeansEndYear": null, "id": 59409625, "sectionNumber": "152"}, {"stateAgencyBalance": null, "budgetActivityEndYear": null, "totalEndYear": null, "budgetActivityBeginYear": null, "entityClass": "ru.lanit.gmu.priv.model.document.BalanceItem", "name": "\u043f\u043e\u0441\u0442\u0443\u043f\u043b\u0435\u043d\u0438\u044f \u043e\u0442 \u043c\u0435\u0436\u0434\u0443\u043d\u0430\u0440\u043e\u0434\u043d\u044b\u0445 \u0444\u0438\u043d\u0430\u043d\u0441\u043e\u0432\u044b\u0445 \u043e\u0440\u0433\u0430\u043d\u0438\u0437\u0430\u0446\u0438\u0439", "totalBeginYear": null, "incomeActivityEndYear": null, "availableMeansBeginYear": null, "lineCode": "063", "incomeActivityBeginYear": null, "position": 0, "availableMeansEndYear": null, "id": 59409626, "sectionNumber": "153"}, {"stateAgencyBalance": null, "budgetActivityEndYear": null, "totalEndYear": "502,074.41", "budgetActivityBeginYear": null, "entityClass": "ru.lanit.gmu.priv.model.document.BalanceItem", "name": "\u0414\u043e\u0445\u043e\u0434\u044b \u043e\u0442 \u043e\u043f\u0435\u0440\u0430\u0446\u0438\u0439 \u0441 \u0430\u043a\u0442\u0438\u0432\u0430\u043c\u0438", "totalBeginYear": "502,074.41", "incomeActivityEndYear": null, "availableMeansBeginYear": "502,074.41", "lineCode": "090", "incomeActivityBeginYear": null, "position": 0, "availableMeansEndYear": "502,074.41", "id": 59409627, "sectionNumber": "170"}, {"stateAgencyBalance": null, "budgetActivityEndYear": null, "totalEndYear": null, "budgetActivityBeginYear": null, "entityClass": "ru.lanit.gmu.priv.model.document.BalanceItem", "name": "\u0434\u043e\u0445\u043e\u0434\u044b \u043e\u0442 \u043f\u0435\u0440\u0435\u043e\u0446\u0435\u043d\u043a\u0438 \u0430\u043a\u0442\u0438\u0432\u043e\u0432", "totalBeginYear": null, "incomeActivityEndYear": null, "availableMeansBeginYear": null, "lineCode": "091", "incomeActivityBeginYear": null, "position": 0, "availableMeansEndYear": null, "id": 59409628, "sectionNumber": "171"}, {"stateAgencyBalance": null, "budgetActivityEndYear": null, "totalEndYear": "502,074.41", "budgetActivityBeginYear": null, "entityClass": "ru.lanit.gmu.priv.model.document.BalanceItem", "name": "\u0434\u043e\u0445\u043e\u0434\u044b \u043e\u0442 \u0440\u0435\u0430\u043b\u0438\u0437\u0430\u0446\u0438\u0438 \u0430\u043a\u0442\u0438\u0432\u043e\u0432", "totalBeginYear": "502,074.41", "incomeActivityEndYear": null, "availableMeansBeginYear": "502,074.41", "lineCode": "092", "incomeActivityBeginYear": null, "position": 0, "availableMeansEndYear": "502,074.41", "id": 59409629, "sectionNumber": "172"}, {"stateAgencyBalance": null, "budgetActivityEndYear": null, "totalEndYear": "502,074.41", "budgetActivityBeginYear": null, "entityClass": "ru.lanit.gmu.priv.model.document.BalanceItem", "name": "\u0434\u043e\u0445\u043e\u0434\u044b \u043e\u0442 \u0440\u0435\u0430\u043b\u0438\u0437\u0430\u0446\u0438\u0438 \u043d\u0435\u0444\u0438\u043d\u0430\u043d\u0441\u043e\u0432\u044b\u0445 \u0430\u043a\u0442\u0438\u0432\u043e\u0432", "totalBeginYear": "502,074.41", "incomeActivityEndYear": null, "availableMeansBeginYear": "502,074.41", "lineCode": "093", "incomeActivityBeginYear": null, "position": 0, "availableMeansEndYear": "502,074.41", "id": 59409630, "sectionNumber": "172"}, {"stateAgencyBalance": null, "budgetActivityEndYear": null, "totalEndYear": null, "budgetActivityBeginYear": null, "entityClass": "ru.lanit.gmu.priv.model.document.BalanceItem", "name": "\u0434\u043e\u0445\u043e\u0434\u044b \u043e\u0442 \u0440\u0435\u0430\u043b\u0438\u0437\u0430\u0446\u0438\u0438 \u0444\u0438\u043d\u0430\u043d\u0441\u043e\u0432\u044b\u0445 \u0430\u043a\u0442\u0438\u0432\u043e\u0432", "totalBeginYear": null, "incomeActivityEndYear": null, "availableMeansBeginYear": null, "lineCode": "096", "incomeActivityBeginYear": null, "position": 0, "availableMeansEndYear": null, "id": 59409631, "sectionNumber": "172"}, {"stateAgencyBalance": null, "budgetActivityEndYear": null, "totalEndYear": null, "budgetActivityBeginYear": null, "entityClass": "ru.lanit.gmu.priv.model.document.BalanceItem", "name": "\u0447\u0440\u0435\u0437\u0432\u044b\u0447\u0430\u0439\u043d\u044b\u0435 \u0434\u043e\u0445\u043e\u0434\u044b \u043e\u0442 \u043e\u043f\u0435\u0440\u0430\u0446\u0438\u0439 \u0441 \u0430\u043a\u0442\u0438\u0432\u0430\u043c\u0438", "totalBeginYear": null, "incomeActivityEndYear": null, "availableMeansBeginYear": null, "lineCode": "099", "incomeActivityBeginYear": null, "position": 0, "availableMeansEndYear": null, "id": 59409632, "sectionNumber": "173"}, {"stateAgencyBalance": null, "budgetActivityEndYear": "6,206,377.80", "totalEndYear": "376,977,870.64", "budgetActivityBeginYear": "6,206,377.80", "entityClass": "ru.lanit.gmu.priv.model.document.BalanceItem", "name": "\u041f\u0440\u043e\u0447\u0438\u0435 \u0434\u043e\u0445\u043e\u0434\u044b", "totalBeginYear": "376,977,870.64", "incomeActivityEndYear": "370,673,492.84", "availableMeansBeginYear": "98,000.00", "lineCode": "100", "incomeActivityBeginYear": "370,673,492.84", "position": 0, "availableMeansEndYear": "98,000.00", "id": 59409633, "sectionNumber": "180"}, {"stateAgencyBalance": null, "budgetActivityEndYear": "6,206,377.80", "totalEndYear": "375,351,635.15", "budgetActivityBeginYear": "6,206,377.80", "entityClass": "ru.lanit.gmu.priv.model.document.BalanceItem", "name": "\u0441\u0443\u0431\u0441\u0438\u0434\u0438\u0438", "totalBeginYear": "375,351,635.15", "incomeActivityEndYear": "369,145,257.35", "availableMeansBeginYear": null, "lineCode": "101", "incomeActivityBeginYear": "369,145,257.35", "position": 0, "availableMeansEndYear": null, "id": 59409634, "sectionNumber": "180"}, {"stateAgencyBalance": null, "budgetActivityEndYear": null, "totalEndYear": null, "budgetActivityBeginYear": null, "entityClass": "ru.lanit.gmu.priv.model.document.BalanceItem", "name": "\u0441\u0443\u0431\u0441\u0438\u0434\u0438\u0438 \u043d\u0430 \u043e\u0441\u0443\u0449\u0435\u0441\u0442\u0432\u043b\u0435\u043d\u0438\u0435 \u043a\u0430\u043f\u0438\u0442\u0430\u043b\u044c\u043d\u044b\u0445 \u0432\u043b\u043e\u0436\u0435\u043d\u0438\u0439", "totalBeginYear": null, "incomeActivityEndYear": null, "availableMeansBeginYear": null, "lineCode": "102", "incomeActivityBeginYear": null, "position": 0, "availableMeansEndYear": null, "id": 59409635, "sectionNumber": "180"}, {"stateAgencyBalance": null, "budgetActivityEndYear": null, "totalEndYear": "98,000.00", "budgetActivityBeginYear": null, "entityClass": "ru.lanit.gmu.priv.model.document.BalanceItem", "name": "\u0438\u043d\u044b\u0435 \u0442\u0440\u0430\u043d\u0441\u0444\u0435\u0440\u0442\u044b", "totalBeginYear": "98,000.00", "incomeActivityEndYear": null, "availableMeansBeginYear": "98,000.00", "lineCode": "103", "incomeActivityBeginYear": null, "position": 0, "availableMeansEndYear": "98,000.00", "id": 59409636, "sectionNumber": "180"}, {"stateAgencyBalance": null, "budgetActivityEndYear": null, "totalEndYear": "1,528,235.49", "budgetActivityBeginYear": null, "entityClass": "ru.lanit.gmu.priv.model.document.BalanceItem", "name": "\u0438\u043d\u044b\u0435 \u043f\u0440\u043e\u0447\u0438\u0435 \u0434\u043e\u0445\u043e\u0434\u044b ", "totalBeginYear": "1,528,235.49", "incomeActivityEndYear": "1,528,235.49", "availableMeansBeginYear": null, "lineCode": "104", "incomeActivityBeginYear": "1,528,235.49", "position": 0, "availableMeansEndYear": null, "id": 59409637, "sectionNumber": "180"}, {"stateAgencyBalance": null, "budgetActivityEndYear": null, "totalEndYear": null, "budgetActivityBeginYear": null, "entityClass": "ru.lanit.gmu.priv.model.document.BalanceItem", "name": "\u0414\u043e\u0445\u043e\u0434\u044b \u0431\u0443\u0434\u0443\u0449\u0438\u0445 \u043f\u0435\u0440\u0438\u043e\u0434\u043e\u0432", "totalBeginYear": null, "incomeActivityEndYear": null, "availableMeansBeginYear": null, "lineCode": "110", "incomeActivityBeginYear": null, "position": 0, "availableMeansEndYear": null, "id": 59409638, "sectionNumber": "100"}], "status": "P", "entityClass": "ru.lanit.gmu.priv.model.document.AnnualBalanceF0503721", "importedFromVSRI": false, "okato": {"lastModifyDate": 1360327583000, "code1": "45", "code2": "263", "code3": "573", "actual": true, "name": "\u041a\u043e\u0441\u0438\u043d\u043e-\u0423\u0445\u0442\u043e\u043c\u0441\u043a\u0438\u0439", "level": 5, "rootId": 411422, "parentId": 411425, "children": null, "activeFromDate": 1290546000000, "approveDate": null, "oker": null, "activeToDate": null, "code4": "000", "hibernateLazyInitializer": {}, "entityClass": "ru.lanit.gmu.priv.model.nsi.Okato", "id": 411433}, "publishDate": 1458121543955, "okpoCode": "80880239", "financialAssetsTransactions": [{"stateAgencyBalance": null, "budgetActivityEndYear": "-169,509.00", "totalEndYear": "47,618,093.57", "budgetActivityBeginYear": "-169,509.00", "entityClass": "ru.lanit.gmu.priv.model.document.BalanceItem", "name": "\u041e\u043f\u0435\u0440\u0430\u0446\u0438\u0438 \u0441 \u0444\u0438\u043d\u0430\u043d\u0441\u043e\u0432\u044b\u043c\u0438 \u0430\u043a\u0442\u0438\u0432\u0430\u043c\u0438 \u0438 \u043e\u0431\u044f\u0437\u0430\u0442\u0435\u043b\u044c\u0441\u0442\u0432\u0430\u043c\u0438 (\u0441\u0442\u0440.390 \u2013 \u0441\u0442\u0440.510)", "totalBeginYear": "47,618,093.57", "incomeActivityEndYear": "48,158,868.34", "availableMeansBeginYear": "-371,265.77", "lineCode": "380", "incomeActivityBeginYear": "48,158,868.34", "position": 0, "availableMeansEndYear": "-371,265.77", "id": 59409590, "sectionNumber": null}, {"stateAgencyBalance": null, "budgetActivityEndYear": "-169,509.00", "totalEndYear": "49,146,652.78", "budgetActivityBeginYear": "-169,509.00", "entityClass": "ru.lanit.gmu.priv.model.document.BalanceItem", "name": "\u041e\u043f\u0435\u0440\u0430\u0446\u0438\u0438 \u0441 \u0444\u0438\u043d\u0430\u043d\u0441\u043e\u0432\u044b\u043c\u0438 \u0430\u043a\u0442\u0438\u0432\u0430\u043c\u0438 (\u0441\u0442\u0440. 410 + \u0441\u0442\u0440. 420 + \u0441\u0442\u0440. 440 + \u0441\u0442\u0440. 460 + \u0441\u0442\u0440. 470 + \u0441\u0442\u0440. 480)", "totalBeginYear": "49,146,652.78", "incomeActivityEndYear": "49,449,160.29", "availableMeansBeginYear": "-132,998.51", "lineCode": "390", "incomeActivityBeginYear": "49,449,160.29", "position": 0, "availableMeansEndYear": "-132,998.51", "id": 59409591, "sectionNumber": null}, {"stateAgencyBalance": null, "budgetActivityEndYear": "2,188,287.40", "totalEndYear": "50,941,140.08", "budgetActivityBeginYear": "2,188,287.40", "entityClass": "ru.lanit.gmu.priv.model.document.BalanceItem", "name": "\u0427\u0438\u0441\u0442\u043e\u0435 \u043f\u043e\u0441\u0442\u0443\u043f\u043b\u0435\u043d\u0438\u0435 \u0441\u0440\u0435\u0434\u0441\u0442\u0432 \u0443\u0447\u0440\u0435\u0436\u0434\u0435\u043d\u0438\u0439", "totalBeginYear": "50,941,140.08", "incomeActivityEndYear": "49,264,685.97", "availableMeansBeginYear": "-511,833.29", "lineCode": "410", "incomeActivityBeginYear": "49,264,685.97", "position": 0, "availableMeansEndYear": "-511,833.29", "id": 59409592, "sectionNumber": null}, {"stateAgencyBalance": null, "budgetActivityEndYear": "9,383,009.00", "totalEndYear": "408,182,486.78", "budgetActivityBeginYear": "9,383,009.00", "entityClass": "ru.lanit.gmu.priv.model.document.BalanceItem", "name": "\u043f\u043e\u0441\u0442\u0443\u043f\u043b\u0435\u043d\u0438\u0435 \u0441\u0440\u0435\u0434\u0441\u0442\u0432", "totalBeginYear": "408,182,486.78", "incomeActivityEndYear": "374,805,563.68", "availableMeansBeginYear": "23,993,914.10", "lineCode": "411", "incomeActivityBeginYear": "374,805,563.68", "position": 0, "availableMeansEndYear": "23,993,914.10", "id": 59409593, "sectionNumber": "510"}, {"stateAgencyBalance": null, "budgetActivityEndYear": "7,194,721.60", "totalEndYear": "357,241,346.70", "budgetActivityBeginYear": "7,194,721.60", "entityClass": "ru.lanit.gmu.priv.model.document.BalanceItem", "name": "\u0432\u044b\u0431\u044b\u0442\u0438\u0435 \u0441\u0440\u0435\u0434\u0441\u0442\u0432", "totalBeginYear": "357,241,346.70", "incomeActivityEndYear": "325,540,877.71", "availableMeansBeginYear": "24,505,747.39", "lineCode": "412", "incomeActivityBeginYear": "325,540,877.71", "position": 0, "availableMeansEndYear": "24,505,747.39", "id": 59409594, "sectionNumber": "610"}, {"stateAgencyBalance": null, "budgetActivityEndYear": null, "totalEndYear": null, "budgetActivityBeginYear": null, "entityClass": "ru.lanit.gmu.priv.model.document.BalanceItem", "name": "\u0427\u0438\u0441\u0442\u043e\u0435 \u043f\u043e\u0441\u0442\u0443\u043f\u043b\u0435\u043d\u0438\u0435 \u0446\u0435\u043d\u043d\u044b\u0445 \u0431\u0443\u043c\u0430\u0433, \u043a\u0440\u043e\u043c\u0435 \u0430\u043a\u0446\u0438\u0439", "totalBeginYear": null, "incomeActivityEndYear": null, "availableMeansBeginYear": null, "lineCode": "420", "incomeActivityBeginYear": null, "position": 0, "availableMeansEndYear": null, "id": 59409595, "sectionNumber": null}, {"stateAgencyBalance": null, "budgetActivityEndYear": null, "totalEndYear": null, "budgetActivityBeginYear": null, "entityClass": "ru.lanit.gmu.priv.model.document.BalanceItem", "name": "\u0443\u0432\u0435\u043b\u0438\u0447\u0435\u043d\u0438\u0435 \u0441\u0442\u043e\u0438\u043c\u043e\u0441\u0442\u0438 \u0446\u0435\u043d\u043d\u044b\u0445 \u0431\u0443\u043c\u0430\u0433, \u043a\u0440\u043e\u043c\u0435 \u0430\u043a\u0446\u0438\u0439", "totalBeginYear": null, "incomeActivityEndYear": null, "availableMeansBeginYear": null, "lineCode": "421", "incomeActivityBeginYear": null, "position": 0, "availableMeansEndYear": null, "id": 59409596, "sectionNumber": "520"}, {"stateAgencyBalance": null, "budgetActivityEndYear": null, "totalEndYear": null, "budgetActivityBeginYear": null, "entityClass": "ru.lanit.gmu.priv.model.document.BalanceItem", "name": "\u0443\u043c\u0435\u043d\u044c\u0448\u0435\u043d\u0438\u0435 \u0441\u0442\u043e\u0438\u043c\u043e\u0441\u0442\u0438 \u0446\u0435\u043d\u043d\u044b\u0445 \u0431\u0443\u043c\u0430\u0433, \u043a\u0440\u043e\u043c\u0435 \u0430\u043a\u0446\u0438\u0439", "totalBeginYear": null, "incomeActivityEndYear": null, "availableMeansBeginYear": null, "lineCode": "422", "incomeActivityBeginYear": null, "position": 0, "availableMeansEndYear": null, "id": 59409597, "sectionNumber": "620"}, {"stateAgencyBalance": null, "budgetActivityEndYear": null, "totalEndYear": null, "budgetActivityBeginYear": null, "entityClass": "ru.lanit.gmu.priv.model.document.BalanceItem", "name": "\u0427\u0438\u0441\u0442\u043e\u0435 \u043f\u043e\u0441\u0442\u0443\u043f\u043b\u0435\u043d\u0438\u0435 \u0430\u043a\u0446\u0438\u0439 \u0438 \u0438\u043d\u044b\u0445 \u0444\u043e\u0440\u043c \u0443\u0447\u0430\u0441\u0442\u0438\u044f \u0432 \u043a\u0430\u043f\u0438\u0442\u0430\u043b\u0435", "totalBeginYear": null, "incomeActivityEndYear": null, "availableMeansBeginYear": null, "lineCode": "440", "incomeActivityBeginYear": null, "position": 0, "availableMeansEndYear": null, "id": 59409598, "sectionNumber": null}, {"stateAgencyBalance": null, "budgetActivityEndYear": null, "totalEndYear": null, "budgetActivityBeginYear": null, "entityClass": "ru.lanit.gmu.priv.model.document.BalanceItem", "name": "\u0443\u0432\u0435\u043b\u0438\u0447\u0435\u043d\u0438\u0435 \u0441\u0442\u043e\u0438\u043c\u043e\u0441\u0442\u0438 \u0430\u043a\u0446\u0438\u0439 \u0438 \u0438\u043d\u044b\u0445 \u0444\u043e\u0440\u043c \u0443\u0447\u0430\u0441\u0442\u0438\u044f \u0432 \u043a\u0430\u043f\u0438\u0442\u0430\u043b\u0435", "totalBeginYear": null, "incomeActivityEndYear": null, "availableMeansBeginYear": null, "lineCode": "441", "incomeActivityBeginYear": null, "position": 0, "availableMeansEndYear": null, "id": 59409599, "sectionNumber": "530"}, {"stateAgencyBalance": null, "budgetActivityEndYear": null, "totalEndYear": null, "budgetActivityBeginYear": null, "entityClass": "ru.lanit.gmu.priv.model.document.BalanceItem", "name": "\u0443\u043c\u0435\u043d\u044c\u0448\u0435\u043d\u0438\u0435 \u0441\u0442\u043e\u0438\u043c\u043e\u0441\u0442\u0438 \u0430\u043a\u0446\u0438\u0439 \u0438 \u0438\u043d\u044b\u0445 \u0444\u043e\u0440\u043c \u0443\u0447\u0430\u0441\u0442\u0438\u044f \u0432 \u043a\u0430\u043f\u0438\u0442\u0430\u043b\u0435", "totalBeginYear": null, "incomeActivityEndYear": null, "availableMeansBeginYear": null, "lineCode": "442", "incomeActivityBeginYear": null, "position": 0, "availableMeansEndYear": null, "id": 59409600, "sectionNumber": "630"}, {"stateAgencyBalance": null, "budgetActivityEndYear": null, "totalEndYear": null, "budgetActivityBeginYear": null, "entityClass": "ru.lanit.gmu.priv.model.document.BalanceItem", "name": "\u0427\u0438\u0441\u0442\u043e\u0435 \u043f\u0440\u0435\u0434\u043e\u0441\u0442\u0430\u0432\u043b\u0435\u043d\u0438\u0435 \u0437\u0430\u0439\u043c\u043e\u0432 (\u0441\u0441\u0443\u0434)", "totalBeginYear": null, "incomeActivityEndYear": null, "availableMeansBeginYear": null, "lineCode": "460", "incomeActivityBeginYear": null, "position": 0, "availableMeansEndYear": null, "id": 59409601, "sectionNumber": null}, {"stateAgencyBalance": null, "budgetActivityEndYear": null, "totalEndYear": null, "budgetActivityBeginYear": null, "entityClass": "ru.lanit.gmu.priv.model.document.BalanceItem", "name": "\u0443\u0432\u0435\u043b\u0438\u0447\u0435\u043d\u0438\u0435 \u0437\u0430\u0434\u043e\u043b\u0436\u0435\u043d\u043d\u043e\u0441\u0442\u0438 \u043f\u043e \u043f\u0440\u0435\u0434\u043e\u0441\u0442\u0430\u0432\u043b\u0435\u043d\u043d\u044b\u043c \u0437\u0430\u0439\u043c\u0430\u043c (\u0441\u0441\u0443\u0434\u0430\u043c)", "totalBeginYear": null, "incomeActivityEndYear": null, "availableMeansBeginYear": null, "lineCode": "461", "incomeActivityBeginYear": null, "position": 0, "availableMeansEndYear": null, "id": 59409602, "sectionNumber": "540"}, {"stateAgencyBalance": null, "budgetActivityEndYear": null, "totalEndYear": null, "budgetActivityBeginYear": null, "entityClass": "ru.lanit.gmu.priv.model.document.BalanceItem", "name": "\u0443\u043c\u0435\u043d\u044c\u0448\u0435\u043d\u0438\u0435 \u0437\u0430\u0434\u043e\u043b\u0436\u0435\u043d\u043d\u043e\u0441\u0442\u0438 \u043f\u043e \u043f\u0440\u0435\u0434\u043e\u0441\u0442\u0430\u0432\u043b\u0435\u043d\u043d\u044b\u043c \u0437\u0430\u0439\u043c\u0430\u043c (\u0441\u0441\u0443\u0434\u0430\u043c)", "totalBeginYear": null, "incomeActivityEndYear": null, "availableMeansBeginYear": null, "lineCode": "462", "incomeActivityBeginYear": null, "position": 0, "availableMeansEndYear": null, "id": 59409603, "sectionNumber": "640"}, {"stateAgencyBalance": null, "budgetActivityEndYear": null, "totalEndYear": null, "budgetActivityBeginYear": null, "entityClass": "ru.lanit.gmu.priv.model.document.BalanceItem", "name": "\u0427\u0438\u0441\u0442\u043e\u0435 \u043f\u043e\u0441\u0442\u0443\u043f\u043b\u0435\u043d\u0438\u0435 \u0438\u043d\u044b\u0445 \u0444\u0438\u043d\u0430\u043d\u0441\u043e\u0432\u044b\u0445 \u0430\u043a\u0442\u0438\u0432\u043e\u0432", "totalBeginYear": null, "incomeActivityEndYear": null, "availableMeansBeginYear": null, "lineCode": "470", "incomeActivityBeginYear": null, "position": 0, "availableMeansEndYear": null, "id": 59409604, "sectionNumber": null}, {"stateAgencyBalance": null, "budgetActivityEndYear": null, "totalEndYear": null, "budgetActivityBeginYear": null, "entityClass": "ru.lanit.gmu.priv.model.document.BalanceItem", "name": "\u0443\u0432\u0435\u043b\u0438\u0447\u0435\u043d\u0438\u0435 \u0441\u0442\u043e\u0438\u043c\u043e\u0441\u0442\u0438 \u0438\u043d\u044b\u0445 \u0444\u0438\u043d\u0430\u043d\u0441\u043e\u0432\u044b\u0445 \u0430\u043a\u0442\u0438\u0432\u043e\u0432", "totalBeginYear": null, "incomeActivityEndYear": null, "availableMeansBeginYear": null, "lineCode": "471", "incomeActivityBeginYear": null, "position": 0, "availableMeansEndYear": null, "id": 59409605, "sectionNumber": "550"}, {"stateAgencyBalance": null, "budgetActivityEndYear": null, "totalEndYear": null, "budgetActivityBeginYear": null, "entityClass": "ru.lanit.gmu.priv.model.document.BalanceItem", "name": "\u0443\u043c\u0435\u043d\u044c\u0448\u0435\u043d\u0438\u0435 \u0441\u0442\u043e\u0438\u043c\u043e\u0441\u0442\u0438 \u0438\u043d\u044b\u0445 \u0444\u0438\u043d\u0430\u043d\u0441\u043e\u0432\u044b\u0445 \u0430\u043a\u0442\u0438\u0432\u043e\u0432", "totalBeginYear": null, "incomeActivityEndYear": null, "availableMeansBeginYear": null, "lineCode": "472", "incomeActivityBeginYear": null, "position": 0, "availableMeansEndYear": null, "id": 59409606, "sectionNumber": "650"}, {"stateAgencyBalance": null, "budgetActivityEndYear": "-2,357,796.40", "totalEndYear": "-1,794,487.30", "budgetActivityBeginYear": "-2,357,796.40", "entityClass": "ru.lanit.gmu.priv.model.document.BalanceItem", "name": "\u0427\u0438\u0441\u0442\u043e\u0435 \u0443\u0432\u0435\u043b\u0438\u0447\u0435\u043d\u0438\u0435 \u0434\u0435\u0431\u0438\u0442\u043e\u0440\u0441\u043a\u043e\u0439 \u0437\u0430\u0434\u043e\u043b\u0436\u0435\u043d\u043d\u043e\u0441\u0442\u0438", "totalBeginYear": "-1,794,487.30", "incomeActivityEndYear": "184,474.32", "availableMeansBeginYear": "378,834.78", "lineCode": "480", "incomeActivityBeginYear": "184,474.32", "position": 0, "availableMeansEndYear": "378,834.78", "id": 59409607, "sectionNumber": null}, {"stateAgencyBalance": null, "budgetActivityEndYear": "6,523,842.19", "totalEndYear": "409,340,540.61", "budgetActivityBeginYear": "6,523,842.19", "entityClass": "ru.lanit.gmu.priv.model.document.BalanceItem", "name": "\u0443\u0432\u0435\u043b\u0438\u0447\u0435\u043d\u0438\u0435 \u0434\u0435\u0431\u0438\u0442\u043e\u0440\u0441\u043a\u043e\u0439 \u0437\u0430\u0434\u043e\u043b\u0436\u0435\u043d\u043d\u043e\u0441\u0442\u0438", "totalBeginYear": "409,340,540.61", "incomeActivityEndYear": "379,277,364.81", "availableMeansBeginYear": "23,539,333.61", "lineCode": "481", "incomeActivityBeginYear": "379,277,364.81", "position": 0, "availableMeansEndYear": "23,539,333.61", "id": 59409608, "sectionNumber": "560"}, {"stateAgencyBalance": null, "budgetActivityEndYear": "8,881,638.59", "totalEndYear": "411,135,027.91", "budgetActivityBeginYear": "8,881,638.59", "entityClass": "ru.lanit.gmu.priv.model.document.BalanceItem", "name": "\u0443\u043c\u0435\u043d\u044c\u0448\u0435\u043d\u0438\u0435 \u0434\u0435\u0431\u0438\u0442\u043e\u0440\u0441\u043a\u043e\u0439 \u0437\u0430\u0434\u043e\u043b\u0436\u0435\u043d\u043d\u043e\u0441\u0442\u0438", "totalBeginYear": "411,135,027.91", "incomeActivityEndYear": "379,092,890.49", "availableMeansBeginYear": "23,160,498.83", "lineCode": "482", "incomeActivityBeginYear": "379,092,890.49", "position": 0, "availableMeansEndYear": "23,160,498.83", "id": 59409609, "sectionNumber": "660"}, {"stateAgencyBalance": null, "budgetActivityEndYear": "0.00", "totalEndYear": "1,528,559.21", "budgetActivityBeginYear": null, "entityClass": "ru.lanit.gmu.priv.model.document.BalanceItem", "name": "\u041e\u043f\u0435\u0440\u0430\u0446\u0438\u0438 \u0441 \u043e\u0431\u044f\u0437\u0430\u0442\u0435\u043b\u044c\u0441\u0442\u0432\u0430\u043c\u0438 (\u0441\u0442\u0440. 520 + \u0441\u0442\u0440. 530 + \u0441\u0442\u0440. 540)", "totalBeginYear": "1,528,559.21", "incomeActivityEndYear": "1,290,291.95", "availableMeansBeginYear": "238,267.26", "lineCode": "510", "incomeActivityBeginYear": "1,290,291.95", "position": 0, "availableMeansEndYear": "238,267.26", "id": 59409610, "sectionNumber": null}, {"stateAgencyBalance": null, "budgetActivityEndYear": null, "totalEndYear": null, "budgetActivityBeginYear": null, "entityClass": "ru.lanit.gmu.priv.model.document.BalanceItem", "name": "\u0427\u0438\u0441\u0442\u043e\u0435 \u0443\u0432\u0435\u043b\u0438\u0447\u0435\u043d\u0438\u0435 \u0437\u0430\u0434\u043e\u043b\u0436\u0435\u043d\u043d\u043e\u0441\u0442\u0438 \u043f\u043e \u043f\u0440\u0438\u0432\u043b\u0435\u0447\u0435\u043d\u0438\u044f\u043c \u043f\u0435\u0440\u0435\u0434 \u0440\u0435\u0437\u0438\u0434\u0435\u043d\u0442\u0430\u043c\u0438", "totalBeginYear": null, "incomeActivityEndYear": null, "availableMeansBeginYear": null, "lineCode": "520", "incomeActivityBeginYear": null, "position": 0, "availableMeansEndYear": null, "id": 59409611, "sectionNumber": null}, {"stateAgencyBalance": null, "budgetActivityEndYear": null, "totalEndYear": null, "budgetActivityBeginYear": null, "entityClass": "ru.lanit.gmu.priv.model.document.BalanceItem", "name": "\u0443\u0432\u0435\u043b\u0438\u0447\u0435\u043d\u0438\u0435 \u0437\u0430\u0434\u043e\u043b\u0436\u0435\u043d\u043d\u043e\u0441\u0442\u0438 \u043f\u043e \u043f\u0440\u0438\u0432\u043b\u0435\u0447\u0435\u043d\u0438\u044f\u043c \u043f\u0435\u0440\u0435\u0434 \u0440\u0435\u0437\u0438\u0434\u0435\u043d\u0442\u0430\u043c\u0438", "totalBeginYear": null, "incomeActivityEndYear": null, "availableMeansBeginYear": null, "lineCode": "521", "incomeActivityBeginYear": null, "position": 0, "availableMeansEndYear": null, "id": 59409612, "sectionNumber": "710"}, {"stateAgencyBalance": null, "budgetActivityEndYear": null, "totalEndYear": null, "budgetActivityBeginYear": null, "entityClass": "ru.lanit.gmu.priv.model.document.BalanceItem", "name": "\u0443\u043c\u0435\u043d\u044c\u0448\u0435\u043d\u0438\u0435 \u0437\u0430\u0434\u043e\u043b\u0436\u0435\u043d\u043d\u043e\u0441\u0442\u0438 \u043f\u043e \u043f\u0440\u0438\u0432\u043b\u0435\u0447\u0435\u043d\u0438\u044f\u043c \u043f\u0435\u0440\u0435\u0434 \u0440\u0435\u0437\u0438\u0434\u0435\u043d\u0442\u0430\u043c\u0438", "totalBeginYear": null, "incomeActivityEndYear": null, "availableMeansBeginYear": null, "lineCode": "522", "incomeActivityBeginYear": null, "position": 0, "availableMeansEndYear": null, "id": 59409613, "sectionNumber": "810"}, {"stateAgencyBalance": null, "budgetActivityEndYear": null, "totalEndYear": null, "budgetActivityBeginYear": null, "entityClass": "ru.lanit.gmu.priv.model.document.BalanceItem", "name": "\u0427\u0438\u0441\u0442\u043e\u0435 \u0443\u0432\u0435\u043b\u0438\u0447\u0435\u043d\u0438\u0435 \u0437\u0430\u0434\u043e\u043b\u0436\u0435\u043d\u043d\u043e\u0441\u0442\u0438 \u043f\u043e \u043f\u0440\u0438\u0432\u043b\u0435\u0447\u0435\u043d\u0438\u044f\u043c \u043f\u0435\u0440\u0435\u0434 \u043d\u0435\u0440\u0435\u0437\u0438\u0434\u0435\u043d\u0442\u0430\u043c\u0438", "totalBeginYear": null, "incomeActivityEndYear": null, "availableMeansBeginYear": null, "lineCode": "530", "incomeActivityBeginYear": null, "position": 0, "availableMeansEndYear": null, "id": 59409614, "sectionNumber": null}, {"stateAgencyBalance": null, "budgetActivityEndYear": null, "totalEndYear": null, "budgetActivityBeginYear": null, "entityClass": "ru.lanit.gmu.priv.model.document.BalanceItem", "name": "\u0443\u0432\u0435\u043b\u0438\u0447\u0435\u043d\u0438\u0435 \u0437\u0430\u0434\u043e\u043b\u0436\u0435\u043d\u043d\u043e\u0441\u0442\u0438 \u043f\u043e \u043f\u0440\u0438\u0432\u043b\u0435\u0447\u0435\u043d\u0438\u044f\u043c \u043f\u0435\u0440\u0435\u0434 \u043d\u0435\u0440\u0435\u0437\u0438\u0434\u0435\u043d\u0442\u0430\u043c\u0438", "totalBeginYear": null, "incomeActivityEndYear": null, "availableMeansBeginYear": null, "lineCode": "531", "incomeActivityBeginYear": null, "position": 0, "availableMeansEndYear": null, "id": 59409615, "sectionNumber": "720"}, {"stateAgencyBalance": null, "budgetActivityEndYear": null, "totalEndYear": null, "budgetActivityBeginYear": null, "entityClass": "ru.lanit.gmu.priv.model.document.BalanceItem", "name": "\u0443\u043c\u0435\u043d\u044c\u0448\u0435\u043d\u0438\u0435 \u0437\u0430\u0434\u043e\u043b\u0436\u0435\u043d\u043d\u043e\u0441\u0442\u0438 \u043f\u043e \u043f\u0440\u0438\u0432\u043b\u0435\u0447\u0435\u043d\u0438\u044f\u043c \u043f\u0435\u0440\u0435\u0434 \u043d\u0435\u0440\u0435\u0437\u0438\u0434\u0435\u043d\u0442\u0430\u043c\u0438", "totalBeginYear": null, "incomeActivityEndYear": null, "availableMeansBeginYear": null, "lineCode": "532", "incomeActivityBeginYear": null, "position": 0, "availableMeansEndYear": null, "id": 59409616, "sectionNumber": "820"}, {"stateAgencyBalance": null, "budgetActivityEndYear": "0.00", "totalEndYear": "1,528,559.21", "budgetActivityBeginYear": null, "entityClass": "ru.lanit.gmu.priv.model.document.BalanceItem", "name": "\u0427\u0438\u0441\u0442\u043e\u0435 \u0443\u0432\u0435\u043b\u0438\u0447\u0435\u043d\u0438\u0435 \u043f\u0440\u043e\u0447\u0435\u0439 \u043a\u0440\u0435\u0434\u0438\u0442\u043e\u0440\u0441\u043a\u043e\u0439 \u0437\u0430\u0434\u043e\u043b\u0436\u0435\u043d\u043d\u043e\u0441\u0442\u0438", "totalBeginYear": "1,528,559.21", "incomeActivityEndYear": "1,290,291.95", "availableMeansBeginYear": "238,267.26", "lineCode": "540", "incomeActivityBeginYear": "1,290,291.95", "position": 0, "availableMeansEndYear": "238,267.26", "id": 59409617, "sectionNumber": null}, {"stateAgencyBalance": null, "budgetActivityEndYear": "6,375,886.80", "totalEndYear": "608,948,712.93", "budgetActivityBeginYear": "6,375,886.80", "entityClass": "ru.lanit.gmu.priv.model.document.BalanceItem", "name": "\u0443\u0432\u0435\u043b\u0438\u0447\u0435\u043d\u0438\u0435 \u043f\u0440\u043e\u0447\u0435\u0439 \u043a\u0440\u0435\u0434\u0438\u0442\u043e\u0440\u0441\u043a\u043e\u0439 \u0437\u0430\u0434\u043e\u043b\u0436\u0435\u043d\u043d\u043e\u0441\u0442\u0438", "totalBeginYear": "608,948,712.93", "incomeActivityEndYear": "565,313,847.66", "availableMeansBeginYear": "37,258,978.47", "lineCode": "541", "incomeActivityBeginYear": "565,313,847.66", "position": 0, "availableMeansEndYear": "37,258,978.47", "id": 59409618, "sectionNumber": "730"}, {"stateAgencyBalance": null, "budgetActivityEndYear": "6,375,886.80", "totalEndYear": "607,420,153.72", "budgetActivityBeginYear": "6,375,886.80", "entityClass": "ru.lanit.gmu.priv.model.document.BalanceItem", "name": "\u0443\u043c\u0435\u043d\u044c\u0448\u0435\u043d\u0438\u0435 \u043f\u0440\u043e\u0447\u0435\u0439 \u043a\u0440\u0435\u0434\u0438\u0442\u043e\u0440\u0441\u043a\u043e\u0439 \u0437\u0430\u0434\u043e\u043b\u0436\u0435\u043d\u043d\u043e\u0441\u0442\u0438", "totalBeginYear": "607,420,153.72", "incomeActivityEndYear": "564,023,555.71", "availableMeansBeginYear": "37,020,711.21", "lineCode": "542", "incomeActivityBeginYear": "564,023,555.71", "position": 0, "availableMeansEndYear": "37,020,711.21", "id": 59409619, "sectionNumber": "830"}], "expenses": [{"stateAgencyBalance": null, "budgetActivityEndYear": "6,409,236.80", "totalEndYear": "338,648,254.41", "budgetActivityBeginYear": "6,409,236.80", "entityClass": "ru.lanit.gmu.priv.model.document.BalanceItem", "name": "\u0420\u0430\u0441\u0445\u043e\u0434\u044b (\u0441\u0442\u0440. 160 + \u0441\u0442\u0440. 170 + \u0441\u0442\u0440. 190 + \u0441\u0442\u0440. 210 + \u0441\u0442\u0440. 230 + \u0441\u0442\u0440. 240 + \u0441\u0442\u0440. 250 + \u0441\u0442\u0440. 260 + \u0441\u0442\u0440. 290)", "totalBeginYear": "360,476,088.76", "incomeActivityEndYear": "332,239,017.61", "availableMeansBeginYear": "21,827,834.35", "lineCode": "150", "incomeActivityBeginYear": "332,239,017.61", "position": 0, "availableMeansEndYear": null, "id": 59409556, "sectionNumber": "200"}, {"stateAgencyBalance": null, "budgetActivityEndYear": null, "totalEndYear": "288,634,481.70", "budgetActivityBeginYear": null, "entityClass": "ru.lanit.gmu.priv.model.document.BalanceItem", "name": "\u041e\u043f\u043b\u0430\u0442\u0430 \u0442\u0440\u0443\u0434\u0430 \u0438 \u043d\u0430\u0447\u0438\u0441\u043b\u0435\u043d\u0438\u044f \u043d\u0430 \u0432\u044b\u043f\u043b\u0430\u0442\u044b \u043f\u043e \u043e\u043f\u043b\u0430\u0442\u0435 \u0442\u0440\u0443\u0434\u0430", "totalBeginYear": "303,143,490.36", "incomeActivityEndYear": "288,634,481.70", "availableMeansBeginYear": null, "lineCode": "160", "incomeActivityBeginYear": "288,634,481.70", "position": 0, "availableMeansEndYear": null, "id": 59409557, "sectionNumber": "210"}, {"stateAgencyBalance": null, "budgetActivityEndYear": null, "totalEndYear": "227,285,487.66", "budgetActivityBeginYear": null, "entityClass": "ru.lanit.gmu.priv.model.document.BalanceItem", "name": "\u0437\u0430\u0440\u0430\u0431\u043e\u0442\u043d\u0430\u044f \u043f\u043b\u0430\u0442\u0430", "totalBeginYear": "238,888,082.29", "incomeActivityEndYear": "227,285,487.66", "availableMeansBeginYear": null, "lineCode": "161", "incomeActivityBeginYear": "227,285,487.66", "position": 0, "availableMeansEndYear": null, "id": 59409558, "sectionNumber": "211"}, {"stateAgencyBalance": null, "budgetActivityEndYear": null, "totalEndYear": "4,102.52", "budgetActivityBeginYear": null, "entityClass": "ru.lanit.gmu.priv.model.document.BalanceItem", "name": "\u043f\u0440\u043e\u0447\u0438\u0435 \u0432\u044b\u043f\u043b\u0430\u0442\u044b", "totalBeginYear": "4,102.52", "incomeActivityEndYear": "4,102.52", "availableMeansBeginYear": null, "lineCode": "162", "incomeActivityBeginYear": "4,102.52", "position": 0, "availableMeansEndYear": null, "id": 59409559, "sectionNumber": "212"}, {"stateAgencyBalance": null, "budgetActivityEndYear": null, "totalEndYear": "61,344,891.52", "budgetActivityBeginYear": null, "entityClass": "ru.lanit.gmu.priv.model.document.BalanceItem", "name": "\u043d\u0430\u0447\u0438\u0441\u043b\u0435\u043d\u0438\u044f \u043d\u0430 \u0432\u044b\u043f\u043b\u0430\u0442\u044b \u043f\u043e \u043e\u043f\u043b\u0430\u0442\u0435 \u0442\u0440\u0443\u0434\u0430", "totalBeginYear": "64,251,305.55", "incomeActivityEndYear": "61,344,891.52", "availableMeansBeginYear": null, "lineCode": "163", "incomeActivityBeginYear": "61,344,891.52", "position": 0, "availableMeansEndYear": null, "id": 59409560, "sectionNumber": "213"}, {"stateAgencyBalance": null, "budgetActivityEndYear": "5,826,524.49", "totalEndYear": "28,456,473.69", "budgetActivityBeginYear": "5,826,524.49", "entityClass": "ru.lanit.gmu.priv.model.document.BalanceItem", "name": "\u041f\u0440\u0438\u043e\u0431\u0440\u0435\u0442\u0435\u043d\u0438\u0435 \u0440\u0430\u0431\u043e\u0442, \u0443\u0441\u043b\u0443\u0433", "totalBeginYear": "32,120,451.84", "incomeActivityEndYear": "22,629,949.20", "availableMeansBeginYear": null, "lineCode": "170", "incomeActivityBeginYear": "22,629,949.20", "position": 0, "availableMeansEndYear": null, "id": 59409561, "sectionNumber": "220"}, {"stateAgencyBalance": null, "budgetActivityEndYear": null, "totalEndYear": "153,636.79", "budgetActivityBeginYear": null, "entityClass": "ru.lanit.gmu.priv.model.document.BalanceItem", "name": "\u0443\u0441\u043b\u0443\u0433\u0438 \u0441\u0432\u044f\u0437\u0438", "totalBeginYear": "180,901.56", "incomeActivityEndYear": "153,636.79", "availableMeansBeginYear": null, "lineCode": "171", "incomeActivityBeginYear": "153,636.79", "position": 0, "availableMeansEndYear": null, "id": 59409562, "sectionNumber": "221"}, {"stateAgencyBalance": null, "budgetActivityEndYear": null, "totalEndYear": "391,780.00", "budgetActivityBeginYear": null, "entityClass": "ru.lanit.gmu.priv.model.document.BalanceItem", "name": "\u0442\u0440\u0430\u043d\u0441\u043f\u043e\u0440\u0442\u043d\u044b\u0435 \u0443\u0441\u043b\u0443\u0433\u0438", "totalBeginYear": "391,780.00", "incomeActivityEndYear": "391,780.00", "availableMeansBeginYear": null, "lineCode": "172", "incomeActivityBeginYear": "391,780.00", "position": 0, "availableMeansEndYear": null, "id": 59409563, "sectionNumber": "222"}, {"stateAgencyBalance": null, "budgetActivityEndYear": null, "totalEndYear": "13,008,428.48", "budgetActivityBeginYear": null, "entityClass": "ru.lanit.gmu.priv.model.document.BalanceItem", "name": "\u043a\u043e\u043c\u043c\u0443\u043d\u0430\u043b\u044c\u043d\u044b\u0435 \u0443\u0441\u043b\u0443\u0433\u0438", "totalBeginYear": "13,043,724.80", "incomeActivityEndYear": "13,008,428.48", "availableMeansBeginYear": null, "lineCode": "173", "incomeActivityBeginYear": "13,008,428.48", "position": 0, "availableMeansEndYear": null, "id": 59409564, "sectionNumber": "223"}, {"stateAgencyBalance": null, "budgetActivityEndYear": null, "totalEndYear": null, "budgetActivityBeginYear": null, "entityClass": "ru.lanit.gmu.priv.model.document.BalanceItem", "name": "\u0430\u0440\u0435\u043d\u0434\u043d\u0430\u044f \u043f\u043b\u0430\u0442\u0430 \u0437\u0430 \u043f\u043e\u043b\u044c\u0437\u043e\u0432\u0430\u043d\u0438\u0435 \u0438\u043c\u0443\u0449\u0435\u0441\u0442\u0432\u043e\u043c", "totalBeginYear": null, "incomeActivityEndYear": null, "availableMeansBeginYear": null, "lineCode": "174", "incomeActivityBeginYear": null, "position": 0, "availableMeansEndYear": null, "id": 59409565, "sectionNumber": "224"}, {"stateAgencyBalance": null, "budgetActivityEndYear": "5,195,874.49", "totalEndYear": "11,888,844.91", "budgetActivityBeginYear": "5,195,874.49", "entityClass": "ru.lanit.gmu.priv.model.document.BalanceItem", "name": "\u0440\u0430\u0431\u043e\u0442\u044b, \u0443\u0441\u043b\u0443\u0433\u0438 \u043f\u043e \u0441\u043e\u0434\u0435\u0440\u0436\u0430\u043d\u0438\u044e \u0438\u043c\u0443\u0449\u0435\u0441\u0442\u0432\u0430", "totalBeginYear": "12,778,602.99", "incomeActivityEndYear": "6,692,970.42", "availableMeansBeginYear": null, "lineCode": "175", "incomeActivityBeginYear": "6,692,970.42", "position": 0, "availableMeansEndYear": null, "id": 59409566, "sectionNumber": "225"}, {"stateAgencyBalance": null, "budgetActivityEndYear": "630,650.00", "totalEndYear": "3,013,783.51", "budgetActivityBeginYear": "630,650.00", "entityClass": "ru.lanit.gmu.priv.model.document.BalanceItem", "name": "\u043f\u0440\u043e\u0447\u0438\u0435 \u0440\u0430\u0431\u043e\u0442\u044b, \u0443\u0441\u043b\u0443\u0433\u0438", "totalBeginYear": "5,725,442.49", "incomeActivityEndYear": "2,383,133.51", "availableMeansBeginYear": null, "lineCode": "176", "incomeActivityBeginYear": "2,383,133.51", "position": 0, "availableMeansEndYear": null, "id": 59409567, "sectionNumber": "226"}, {"stateAgencyBalance": null, "budgetActivityEndYear": null, "totalEndYear": null, "budgetActivityBeginYear": null, "entityClass": "ru.lanit.gmu.priv.model.document.BalanceItem", "name": "\u041e\u0431\u0441\u043b\u0443\u0436\u0438\u0432\u0430\u043d\u0438\u0435 \u0434\u043e\u043b\u0433\u043e\u0432\u044b\u0445 \u043e\u0431\u044f\u0437\u0430\u0442\u0435\u043b\u044c\u0441\u0442\u0432", "totalBeginYear": null, "incomeActivityEndYear": null, "availableMeansBeginYear": null, "lineCode": "190", "incomeActivityBeginYear": null, "position": 0, "availableMeansEndYear": null, "id": 59409568, "sectionNumber": "230"}, {"stateAgencyBalance": null, "budgetActivityEndYear": null, "totalEndYear": null, "budgetActivityBeginYear": null, "entityClass": "ru.lanit.gmu.priv.model.document.BalanceItem", "name": "\u043e\u0431\u0441\u043b\u0443\u0436\u0438\u0432\u0430\u043d\u0438\u0435 \u0434\u043e\u043b\u0433\u043e\u0432\u044b\u0445 \u043e\u0431\u044f\u0437\u0430\u0442\u0435\u043b\u044c\u0441\u0442\u0432 \u043f\u0435\u0440\u0435\u0434 \u0440\u0435\u0437\u0438\u0434\u0435\u043d\u0442\u0430\u043c\u0438", "totalBeginYear": null, "incomeActivityEndYear": null, "availableMeansBeginYear": null, "lineCode": "191", "incomeActivityBeginYear": null, "position": 0, "availableMeansEndYear": null, "id": 59409569, "sectionNumber": "231"}, {"stateAgencyBalance": null, "budgetActivityEndYear": null, "totalEndYear": null, "budgetActivityBeginYear": null, "entityClass": "ru.lanit.gmu.priv.model.document.BalanceItem", "name": "\u043e\u0431\u0441\u043b\u0443\u0436\u0438\u0432\u0430\u043d\u0438\u0435 \u0434\u043e\u043b\u0433\u043e\u0432\u044b\u0445 \u043e\u0431\u044f\u0437\u0430\u0442\u0435\u043b\u044c\u0441\u0442\u0432 \u043f\u0435\u0440\u0435\u0434 \u043d\u0435\u0440\u0435\u0437\u0438\u0434\u0435\u043d\u0442\u0430\u043c\u0438", "totalBeginYear": null, "incomeActivityEndYear": null, "availableMeansBeginYear": null, "lineCode": "192", "incomeActivityBeginYear": null, "position": 0, "availableMeansEndYear": null, "id": 59409570, "sectionNumber": "232"}, {"stateAgencyBalance": null, "budgetActivityEndYear": null, "totalEndYear": null, "budgetActivityBeginYear": null, "entityClass": "ru.lanit.gmu.priv.model.document.BalanceItem", "name": "\u0411\u0435\u0437\u0432\u043e\u0437\u043c\u0435\u0437\u0434\u043d\u044b\u0435 \u043f\u0435\u0440\u0435\u0447\u0438\u0441\u043b\u0435\u043d\u0438\u044f \u043e\u0440\u0433\u0430\u043d\u0438\u0437\u0430\u0446\u0438\u044f\u043c", "totalBeginYear": null, "incomeActivityEndYear": null, "availableMeansBeginYear": null, "lineCode": "210", "incomeActivityBeginYear": null, "position": 0, "availableMeansEndYear": null, "id": 59409571, "sectionNumber": "240"}, {"stateAgencyBalance": null, "budgetActivityEndYear": null, "totalEndYear": null, "budgetActivityBeginYear": null, "entityClass": "ru.lanit.gmu.priv.model.document.BalanceItem", "name": "\u0431\u0435\u0437\u0432\u043e\u0437\u043c\u0435\u0437\u0434\u043d\u044b\u0435 \u043f\u0435\u0440\u0435\u0447\u0438\u0441\u043b\u0435\u043d\u0438\u044f \u0433\u043e\u0441\u0443\u0434\u0430\u0440\u0441\u0442\u0432\u0435\u043d\u043d\u044b\u043c \u0438 \u043c\u0443\u043d\u0438\u0446\u0438\u043f\u0430\u043b\u044c\u043d\u044b\u043c \u043e\u0440\u0433\u0430\u043d\u0438\u0437\u0430\u0446\u0438\u044f\u043c", "totalBeginYear": null, "incomeActivityEndYear": null, "availableMeansBeginYear": null, "lineCode": "211", "incomeActivityBeginYear": null, "position": 0, "availableMeansEndYear": null, "id": 59409572, "sectionNumber": "241"}, {"stateAgencyBalance": null, "budgetActivityEndYear": null, "totalEndYear": null, "budgetActivityBeginYear": null, "entityClass": "ru.lanit.gmu.priv.model.document.BalanceItem", "name": "\u0431\u0435\u0437\u0432\u043e\u0437\u043c\u0435\u0437\u0434\u043d\u044b\u0435 \u043f\u0435\u0440\u0435\u0447\u0438\u0441\u043b\u0435\u043d\u0438\u044f \u043e\u0440\u0433\u0430\u043d\u0438\u0437\u0430\u0446\u0438\u044f\u043c, \u0437\u0430 \u0438\u0441\u043a\u043b\u044e\u0447\u0435\u043d\u0438\u0435\u043c \u0433\u043e\u0441\u0443\u0434\u0430\u0440\u0441\u0442\u0432\u0435\u043d\u043d\u044b\u0445 \u0438 \u043c\u0443\u043d\u0438\u0446\u0438\u043f\u0430\u043b\u044c\u043d\u044b\u0445 \u043e\u0440\u0433\u0430\u043d\u0438\u0437\u0430\u0446\u0438\u0439", "totalBeginYear": null, "incomeActivityEndYear": null, "availableMeansBeginYear": null, "lineCode": "212", "incomeActivityBeginYear": null, "position": 0, "availableMeansEndYear": null, "id": 59409573, "sectionNumber": "242"}, {"stateAgencyBalance": null, "budgetActivityEndYear": null, "totalEndYear": null, "budgetActivityBeginYear": null, "entityClass": "ru.lanit.gmu.priv.model.document.BalanceItem", "name": "\u0411\u0435\u0437\u0432\u043e\u0437\u043c\u0435\u0437\u0434\u043d\u044b\u0435 \u043f\u0435\u0440\u0435\u0447\u0438\u0441\u043b\u0435\u043d\u0438\u044f \u0431\u044e\u0434\u0436\u0435\u0442\u0430\u043c", "totalBeginYear": null, "incomeActivityEndYear": null, "availableMeansBeginYear": null, "lineCode": "230", "incomeActivityBeginYear": null, "position": 0, "availableMeansEndYear": null, "id": 59409574, "sectionNumber": "250"}, {"stateAgencyBalance": null, "budgetActivityEndYear": null, "totalEndYear": null, "budgetActivityBeginYear": null, "entityClass": "ru.lanit.gmu.priv.model.document.BalanceItem", "name": "\u043f\u0435\u0440\u0435\u0447\u0438\u0441\u043b\u0435\u043d\u0438\u044f \u043d\u0430\u0434\u043d\u0430\u0446\u0438\u043e\u043d\u0430\u043b\u044c\u043d\u044b\u043c \u043e\u0440\u0433\u0430\u043d\u0438\u0437\u0430\u0446\u0438\u044f\u043c \u0438 \u043f\u0440\u0430\u0432\u0438\u0442\u0435\u043b\u044c\u0441\u0442\u0432\u0430\u043c \u0438\u043d\u043e\u0441\u0442\u0440\u0430\u043d\u043d\u044b\u0445 \u0433\u043e\u0441\u0443\u0434\u0430\u0440\u0441\u0442\u0432", "totalBeginYear": null, "incomeActivityEndYear": null, "availableMeansBeginYear": null, "lineCode": "232", "incomeActivityBeginYear": null, "position": 0, "availableMeansEndYear": null, "id": 59409575, "sectionNumber": "252"}, {"stateAgencyBalance": null, "budgetActivityEndYear": null, "totalEndYear": null, "budgetActivityBeginYear": null, "entityClass": "ru.lanit.gmu.priv.model.document.BalanceItem", "name": "\u043f\u0435\u0440\u0435\u0447\u0438\u0441\u043b\u0435\u043d\u0438\u044f \u043c\u0435\u0436\u0434\u0443\u043d\u0430\u0440\u043e\u0434\u043d\u044b\u043c \u043e\u0440\u0433\u0430\u043d\u0438\u0437\u0430\u0446\u0438\u044f\u043c", "totalBeginYear": null, "incomeActivityEndYear": null, "availableMeansBeginYear": null, "lineCode": "233", "incomeActivityBeginYear": null, "position": 0, "availableMeansEndYear": null, "id": 59409576, "sectionNumber": "253"}, {"stateAgencyBalance": null, "budgetActivityEndYear": "549,362.31", "totalEndYear": "549,362.31", "budgetActivityBeginYear": "549,362.31", "entityClass": "ru.lanit.gmu.priv.model.document.BalanceItem", "name": "\u0421\u043e\u0446\u0438\u0430\u043b\u044c\u043d\u043e\u0435 \u043e\u0431\u0435\u0441\u043f\u0435\u0447\u0435\u043d\u0438\u0435", "totalBeginYear": "549,362.31", "incomeActivityEndYear": null, "availableMeansBeginYear": null, "lineCode": "240", "incomeActivityBeginYear": null, "position": 0, "availableMeansEndYear": null, "id": 59409577, "sectionNumber": "260"}, {"stateAgencyBalance": null, "budgetActivityEndYear": "549,362.31", "totalEndYear": "549,362.31", "budgetActivityBeginYear": "549,362.31", "entityClass": "ru.lanit.gmu.priv.model.document.BalanceItem", "name": "\u043f\u043e\u0441\u043e\u0431\u0438\u044f \u043f\u043e \u0441\u043e\u0446\u0438\u0430\u043b\u044c\u043d\u043e\u0439 \u043f\u043e\u043c\u043e\u0449\u0438 \u043d\u0430\u0441\u0435\u043b\u0435\u043d\u0438\u044e", "totalBeginYear": "549,362.31", "incomeActivityEndYear": null, "availableMeansBeginYear": null, "lineCode": "242", "incomeActivityBeginYear": null, "position": 0, "availableMeansEndYear": null, "id": 59409578, "sectionNumber": "262"}, {"stateAgencyBalance": null, "budgetActivityEndYear": null, "totalEndYear": null, "budgetActivityBeginYear": null, "entityClass": "ru.lanit.gmu.priv.model.document.BalanceItem", "name": "\u043f\u0435\u043d\u0441\u0438\u0438, \u043f\u043e\u0441\u043e\u0431\u0438\u044f, \u0432\u044b\u043f\u043b\u0430\u0447\u0438\u0432\u0430\u0435\u043c\u044b\u0435 \u043e\u0440\u0433\u0430\u043d\u0438\u0437\u0430\u0446\u0438\u044f\u043c\u0438 \u0441\u0435\u043a\u0442\u043e\u0440\u0430 \u0433\u043e\u0441\u0443\u0434\u0430\u0440\u0441\u0442\u0432\u0435\u043d\u043d\u043e\u0433\u043e \u0443\u043f\u0440\u0430\u0432\u043b\u0435\u043d\u0438\u044f", "totalBeginYear": null, "incomeActivityEndYear": null, "availableMeansBeginYear": null, "lineCode": "243", "incomeActivityBeginYear": null, "position": 0, "availableMeansEndYear": null, "id": 59409579, "sectionNumber": "263"}, {"stateAgencyBalance": null, "budgetActivityEndYear": null, "totalEndYear": "721,258.00", "budgetActivityBeginYear": null, "entityClass": "ru.lanit.gmu.priv.model.document.BalanceItem", "name": "\u041f\u0440\u043e\u0447\u0438\u0435 \u0440\u0430\u0441\u0445\u043e\u0434\u044b", "totalBeginYear": "1,153,476.42", "incomeActivityEndYear": "721,258.00", "availableMeansBeginYear": null, "lineCode": "250", "incomeActivityBeginYear": "721,258.00", "position": 0, "availableMeansEndYear": null, "id": 59409580, "sectionNumber": "290"}, {"stateAgencyBalance": null, "budgetActivityEndYear": "33,350.00", "totalEndYear": "20,286,678.71", "budgetActivityBeginYear": "33,350.00", "entityClass": "ru.lanit.gmu.priv.model.document.BalanceItem", "name": "\u0420\u0430\u0441\u0445\u043e\u0434\u044b \u043f\u043e \u043e\u043f\u0435\u0440\u0430\u0446\u0438\u044f\u043c \u0441 \u0430\u043a\u0442\u0438\u0432\u0430\u043c\u0438", "totalBeginYear": "23,509,307.83", "incomeActivityEndYear": "20,253,328.71", "availableMeansBeginYear": null, "lineCode": "260", "incomeActivityBeginYear": "20,253,328.71", "position": 0, "availableMeansEndYear": null, "id": 59409581, "sectionNumber": "270"}, {"stateAgencyBalance": null, "budgetActivityEndYear": null, "totalEndYear": "16,991,061.39", "budgetActivityBeginYear": null, "entityClass": "ru.lanit.gmu.priv.model.document.BalanceItem", "name": "\u0430\u043c\u043e\u0440\u0442\u0438\u0437\u0430\u0446\u0438\u044f \u043e\u0441\u043d\u043e\u0432\u043d\u044b\u0445 \u0441\u0440\u0435\u0434\u0441\u0442\u0432 \u0438 \u043d\u0435\u043c\u0430\u0442\u0435\u0440\u0438\u0430\u043b\u044c\u043d\u044b\u0445 \u0430\u043a\u0442\u0438\u0432\u043e\u0432", "totalBeginYear": "18,856,663.95", "incomeActivityEndYear": "16,991,061.39", "availableMeansBeginYear": null, "lineCode": "261", "incomeActivityBeginYear": "16,991,061.39", "position": 0, "availableMeansEndYear": null, "id": 59409582, "sectionNumber": "271"}, {"stateAgencyBalance": null, "budgetActivityEndYear": "33,350.00", "totalEndYear": "3,295,617.32", "budgetActivityBeginYear": "33,350.00", "entityClass": "ru.lanit.gmu.priv.model.document.BalanceItem", "name": "\u0440\u0430\u0441\u0445\u043e\u0434\u043e\u0432\u0430\u043d\u0438\u0435 \u043c\u0430\u0442\u0435\u0440\u0438\u0430\u043b\u044c\u043d\u044b\u0445 \u0437\u0430\u043f\u0430\u0441\u043e\u0432", "totalBeginYear": "4,652,643.88", "incomeActivityEndYear": "3,262,267.32", "availableMeansBeginYear": null, "lineCode": "264", "incomeActivityBeginYear": "3,262,267.32", "position": 0, "availableMeansEndYear": null, "id": 59409583, "sectionNumber": "272"}, {"stateAgencyBalance": null, "budgetActivityEndYear": null, "totalEndYear": null, "budgetActivityBeginYear": null, "entityClass": "ru.lanit.gmu.priv.model.document.BalanceItem", "name": "\u0447\u0440\u0435\u0437\u0432\u044b\u0447\u0430\u0439\u043d\u044b\u0435 \u0440\u0430\u0441\u0445\u043e\u0434\u044b \u043f\u043e \u043e\u043f\u0435\u0440\u0430\u0446\u0438\u044f\u043c \u0441 \u0430\u043a\u0442\u0438\u0432\u0430\u043c\u0438", "totalBeginYear": null, "incomeActivityEndYear": null, "availableMeansBeginYear": null, "lineCode": "269", "incomeActivityBeginYear": null, "position": 0, "availableMeansEndYear": null, "id": 59409584, "sectionNumber": "273"}, {"stateAgencyBalance": null, "budgetActivityEndYear": null, "totalEndYear": null, "budgetActivityBeginYear": null, "entityClass": "ru.lanit.gmu.priv.model.document.BalanceItem", "name": "\u0420\u0430\u0441\u0445\u043e\u0434\u044b \u0431\u0443\u0434\u0443\u0449\u0438\u0445 \u043f\u0435\u0440\u0438\u043e\u0434\u043e\u0432", "totalBeginYear": null, "incomeActivityEndYear": null, "availableMeansBeginYear": null, "lineCode": "290", "incomeActivityBeginYear": null, "position": 0, "availableMeansEndYear": null, "id": 59409585, "sectionNumber": null}, {"stateAgencyBalance": null, "budgetActivityEndYear": "-202,859.00", "totalEndYear": "62,166,449.65", "budgetActivityBeginYear": "-202,859.00", "entityClass": "ru.lanit.gmu.priv.model.document.BalanceItem", "name": "\u0427\u0438\u0441\u0442\u044b\u0439 \u043e\u043f\u0435\u0440\u0430\u0446\u0438\u043e\u043d\u043d\u044b\u0439 \u0440\u0435\u0437\u0443\u043b\u044c\u0442\u0430\u0442 (\u0441\u0442\u0440. 301\u2013\u0441\u0442\u0440. 302+\u0441\u0442\u0440. 303); (\u0441\u0442\u0440. 310+\u0441\u0442\u0440. 380)", "totalBeginYear": "40,334,215.30", "incomeActivityEndYear": "38,434,475.23", "availableMeansBeginYear": "2,102,599.07", "lineCode": "300", "incomeActivityBeginYear": "38,434,475.23", "position": 0, "availableMeansEndYear": "23,934,833.42", "id": 59409586, "sectionNumber": null}, {"stateAgencyBalance": null, "budgetActivityEndYear": "-202,859.00", "totalEndYear": "62,166,449.65", "budgetActivityBeginYear": "-202,859.00", "entityClass": "ru.lanit.gmu.priv.model.document.BalanceItem", "name": "\u041e\u043f\u0435\u0440\u0430\u0446\u0438\u043e\u043d\u043d\u044b\u0439 \u0440\u0435\u0437\u0443\u043b\u044c\u0442\u0430\u0442 \u0434\u043e \u043d\u0430\u043b\u043e\u0433\u043e\u043e\u0431\u043b\u043e\u0436\u0435\u043d\u0438\u044f (\u0441\u0442\u0440. 010-\u0441\u0442\u0440. 150)", "totalBeginYear": "40,338,615.30", "incomeActivityEndYear": "38,434,475.23", "availableMeansBeginYear": "2,106,999.07", "lineCode": "301", "incomeActivityBeginYear": "38,434,475.23", "position": 0, "availableMeansEndYear": "23,934,833.42", "id": 59409587, "sectionNumber": null}, {"stateAgencyBalance": null, "budgetActivityEndYear": null, "totalEndYear": null, "budgetActivityBeginYear": null, "entityClass": "ru.lanit.gmu.priv.model.document.BalanceItem", "name": "\u041d\u0430\u043b\u043e\u0433 \u043d\u0430 \u043f\u0440\u0438\u0431\u044b\u043b\u044c", "totalBeginYear": "4,400.00", "incomeActivityEndYear": null, "availableMeansBeginYear": null, "lineCode": "302", "incomeActivityBeginYear": null, "position": 0, "availableMeansEndYear": null, "id": 59409588, "sectionNumber": null}, {"stateAgencyBalance": null, "budgetActivityEndYear": null, "totalEndYear": null, "budgetActivityBeginYear": null, "entityClass": "ru.lanit.gmu.priv.model.document.BalanceItem", "name": "\u0420\u0435\u0437\u0435\u0440\u0432\u044b \u043f\u0440\u0435\u0434\u0441\u0442\u043e\u044f\u0449\u0438\u0445 \u0440\u0430\u0441\u0445\u043e\u0434\u043e\u0432", "totalBeginYear": null, "incomeActivityEndYear": null, "availableMeansBeginYear": null, "lineCode": "303", "incomeActivityBeginYear": null, "position": 0, "availableMeansEndYear": null, "id": 59409589, "sectionNumber": null}], "founderCheckResult": null, "founderOkpoCode": "02110342", "founderCheckPrintFormId": null, "agencyName": "\u0413\u041e\u0421\u0423\u0414\u0410\u0420\u0421\u0422\u0412\u0415\u041d\u041d\u041e\u0415 \u0411\u042e\u0414\u0416\u0415\u0422\u041d\u041e\u0415 \u041e\u0411\u0429\u0415\u041e\u0411\u0420\u0410\u0417\u041e\u0412\u0410\u0422\u0415\u041b\u042c\u041d\u041e\u0415 \u0423\u0427\u0420\u0415\u0416\u0414\u0415\u041d\u0418\u0415 \u0413\u041e\u0420\u041e\u0414\u0410 \u041c\u041e\u0421\u041a\u0412\u042b \"\u0428\u041a\u041e\u041b\u0410 \u2116 2031\"", "violationsProtocolMetaInfo": null, "classified": null, "printFormId": 10834558, "okud": "0503721", "nonfinancialAssetsTransactions": [{"stateAgencyBalance": null, "budgetActivityEndYear": "-33,350.00", "totalEndYear": "-7,283,878.27", "budgetActivityBeginYear": "-33,350.00", "entityClass": "ru.lanit.gmu.priv.model.document.BalanceItem", "name": "\u041e\u043f\u0435\u0440\u0430\u0446\u0438\u0438 \u0441 \u043d\u0435\u0444\u0438\u043d\u0430\u043d\u0441\u043e\u0432\u044b\u043c\u0438 \u0430\u043a\u0442\u0438\u0432\u0430\u043c\u0438 (\u0441\u0442\u0440. 320+\u0441\u0442\u0440. 330+\u0441\u0442\u0440. 350+\u0441\u0442\u0440. 360+\u0441\u0442\u0440. 370)", "totalBeginYear": "-7,283,878.27", "incomeActivityEndYear": "-9,724,393.11", "availableMeansBeginYear": "2,473,864.84", "lineCode": "310", "incomeActivityBeginYear": "-9,724,393.11", "position": 0, "availableMeansEndYear": "2,473,864.84", "id": 59409639, "sectionNumber": null}, {"stateAgencyBalance": null, "budgetActivityEndYear": null, "totalEndYear": "-10,529,722.88", "budgetActivityBeginYear": null, "entityClass": "ru.lanit.gmu.priv.model.document.BalanceItem", "name": "\u0427\u0438\u0441\u0442\u043e\u0435 \u043f\u043e\u0441\u0442\u0443\u043f\u043b\u0435\u043d\u0438\u0435 \u043e\u0441\u043d\u043e\u0432\u043d\u044b\u0445 \u0441\u0440\u0435\u0434\u0441\u0442\u0432", "totalBeginYear": "-10,529,722.88", "incomeActivityEndYear": "-11,987,454.74", "availableMeansBeginYear": "1,457,731.86", "lineCode": "320", "incomeActivityBeginYear": "-11,987,454.74", "position": 0, "availableMeansEndYear": "1,457,731.86", "id": 59409640, "sectionNumber": null}, {"stateAgencyBalance": null, "budgetActivityEndYear": null, "totalEndYear": "9,183,955.48", "budgetActivityBeginYear": null, "entityClass": "ru.lanit.gmu.priv.model.document.BalanceItem", "name": "\u0443\u0432\u0435\u043b\u0438\u0447\u0435\u043d\u0438\u0435 \u0441\u0442\u043e\u0438\u043c\u043e\u0441\u0442\u0438 \u043e\u0441\u043d\u043e\u0432\u043d\u044b\u0445 \u0441\u0440\u0435\u0434\u0441\u0442\u0432", "totalBeginYear": "9,183,955.48", "incomeActivityEndYear": "5,003,606.65", "availableMeansBeginYear": "4,180,348.83", "lineCode": "321", "incomeActivityBeginYear": "5,003,606.65", "position": 0, "availableMeansEndYear": "4,180,348.83", "id": 59409641, "sectionNumber": "310"}, {"stateAgencyBalance": null, "budgetActivityEndYear": null, "totalEndYear": "19,713,678.36", "budgetActivityBeginYear": null, "entityClass": "ru.lanit.gmu.priv.model.document.BalanceItem", "name": "\u0443\u043c\u0435\u043d\u044c\u0448\u0435\u043d\u0438\u0435 \u0441\u0442\u043e\u0438\u043c\u043e\u0441\u0442\u0438 \u043e\u0441\u043d\u043e\u0432\u043d\u044b\u0445 \u0441\u0440\u0435\u0434\u0441\u0442\u0432", "totalBeginYear": "19,713,678.36", "incomeActivityEndYear": "16,991,061.39", "availableMeansBeginYear": "2,722,616.97", "lineCode": "322", "incomeActivityBeginYear": "16,991,061.39", "position": 0, "availableMeansEndYear": "2,722,616.97", "id": 59409642, "sectionNumber": "410"}, {"stateAgencyBalance": null, "budgetActivityEndYear": null, "totalEndYear": null, "budgetActivityBeginYear": null, "entityClass": "ru.lanit.gmu.priv.model.document.BalanceItem", "name": "\u0427\u0438\u0441\u0442\u043e\u0435 \u043f\u043e\u0441\u0442\u0443\u043f\u043b\u0435\u043d\u0438\u0435 \u043d\u0435\u043c\u0430\u0442\u0435\u0440\u0438\u0430\u043b\u044c\u043d\u044b\u0445 \u0430\u043a\u0442\u0438\u0432\u043e\u0432", "totalBeginYear": null, "incomeActivityEndYear": null, "availableMeansBeginYear": null, "lineCode": "330", "incomeActivityBeginYear": null, "position": 0, "availableMeansEndYear": null, "id": 59409643, "sectionNumber": null}, {"stateAgencyBalance": null, "budgetActivityEndYear": null, "totalEndYear": null, "budgetActivityBeginYear": null, "entityClass": "ru.lanit.gmu.priv.model.document.BalanceItem", "name": "\u0443\u0432\u0435\u043b\u0438\u0447\u0435\u043d\u0438\u0435 \u0441\u0442\u043e\u0438\u043c\u043e\u0441\u0442\u0438 \u043d\u0435\u043c\u0430\u0442\u0435\u0440\u0438\u0430\u043b\u044c\u043d\u044b\u0445 \u0430\u043a\u0442\u0438\u0432\u043e\u0432", "totalBeginYear": null, "incomeActivityEndYear": null, "availableMeansBeginYear": null, "lineCode": "331", "incomeActivityBeginYear": null, "position": 0, "availableMeansEndYear": null, "id": 59409644, "sectionNumber": "320"}, {"stateAgencyBalance": null, "budgetActivityEndYear": null, "totalEndYear": null, "budgetActivityBeginYear": null, "entityClass": "ru.lanit.gmu.priv.model.document.BalanceItem", "name": "\u0443\u043c\u0435\u043d\u044c\u0448\u0435\u043d\u0438\u0435 \u0441\u0442\u043e\u0438\u043c\u043e\u0441\u0442\u0438 \u043d\u0435\u043c\u0430\u0442\u0435\u0440\u0438\u0430\u043b\u044c\u043d\u044b\u0445 \u0430\u043a\u0442\u0438\u0432\u043e\u0432", "totalBeginYear": null, "incomeActivityEndYear": null, "availableMeansBeginYear": null, "lineCode": "332", "incomeActivityBeginYear": null, "position": 0, "availableMeansEndYear": null, "id": 59409645, "sectionNumber": "420"}, {"stateAgencyBalance": null, "budgetActivityEndYear": null, "totalEndYear": null, "budgetActivityBeginYear": null, "entityClass": "ru.lanit.gmu.priv.model.document.BalanceItem", "name": "\u0427\u0438\u0441\u0442\u043e\u0435 \u043f\u043e\u0441\u0442\u0443\u043f\u043b\u0435\u043d\u0438\u0435 \u043d\u0435\u043f\u0440\u043e\u0438\u0437\u0432\u0435\u0434\u0435\u043d\u043d\u044b\u0445 \u0430\u043a\u0442\u0438\u0432\u043e\u0432", "totalBeginYear": null, "incomeActivityEndYear": null, "availableMeansBeginYear": null, "lineCode": "350", "incomeActivityBeginYear": null, "position": 0, "availableMeansEndYear": null, "id": 59409646, "sectionNumber": null}, {"stateAgencyBalance": null, "budgetActivityEndYear": null, "totalEndYear": null, "budgetActivityBeginYear": null, "entityClass": "ru.lanit.gmu.priv.model.document.BalanceItem", "name": "\u0443\u0432\u0435\u043b\u0438\u0447\u0435\u043d\u0438\u0435 \u0441\u0442\u043e\u0438\u043c\u043e\u0441\u0442\u0438 \u043d\u0435\u043f\u0440\u043e\u0438\u0437\u0432\u0435\u0434\u0435\u043d\u043d\u044b\u0445 \u0430\u043a\u0442\u0438\u0432\u043e\u0432", "totalBeginYear": null, "incomeActivityEndYear": null, "availableMeansBeginYear": null, "lineCode": "351", "incomeActivityBeginYear": null, "position": 0, "availableMeansEndYear": null, "id": 59409647, "sectionNumber": "330"}, {"stateAgencyBalance": null, "budgetActivityEndYear": null, "totalEndYear": null, "budgetActivityBeginYear": null, "entityClass": "ru.lanit.gmu.priv.model.document.BalanceItem", "name": "\u0443\u043c\u0435\u043d\u044c\u0448\u0435\u043d\u0438\u0435 \u0441\u0442\u043e\u0438\u043c\u043e\u0441\u0442\u0438 \u043d\u0435\u043f\u0440\u043e\u0438\u0437\u0432\u0435\u0434\u0435\u043d\u043d\u044b\u0445 \u0430\u043a\u0442\u0438\u0432\u043e\u0432", "totalBeginYear": null, "incomeActivityEndYear": null, "availableMeansBeginYear": null, "lineCode": "352", "incomeActivityBeginYear": null, "position": 0, "availableMeansEndYear": null, "id": 59409648, "sectionNumber": "430"}, {"stateAgencyBalance": null, "budgetActivityEndYear": "-33,350.00", "totalEndYear": "3,245,844.61", "budgetActivityBeginYear": "-33,350.00", "entityClass": "ru.lanit.gmu.priv.model.document.BalanceItem", "name": "\u0427\u0438\u0441\u0442\u043e\u0435 \u043f\u043e\u0441\u0442\u0443\u043f\u043b\u0435\u043d\u0438\u0435 \u043c\u0430\u0442\u0435\u0440\u0438\u0430\u043b\u044c\u043d\u044b\u0445 \u0437\u0430\u043f\u0430\u0441\u043e\u0432", "totalBeginYear": "3,245,844.61", "incomeActivityEndYear": "2,263,061.63", "availableMeansBeginYear": "1,016,132.98", "lineCode": "360", "incomeActivityBeginYear": "2,263,061.63", "position": 0, "availableMeansEndYear": "1,016,132.98", "id": 59409649, "sectionNumber": null}, {"stateAgencyBalance": null, "budgetActivityEndYear": null, "totalEndYear": "7,920,488.49", "budgetActivityBeginYear": null, "entityClass": "ru.lanit.gmu.priv.model.document.BalanceItem", "name": "\u0443\u0432\u0435\u043b\u0438\u0447\u0435\u043d\u0438\u0435 \u0441\u0442\u043e\u0438\u043c\u043e\u0441\u0442\u0438 \u043c\u0430\u0442\u0435\u0440\u0438\u0430\u043b\u044c\u043d\u044b\u0445 \u0437\u0430\u043f\u0430\u0441\u043e\u0432", "totalBeginYear": "7,920,488.49", "incomeActivityEndYear": "5,525,328.95", "availableMeansBeginYear": "2,395,159.54", "lineCode": "361", "incomeActivityBeginYear": "5,525,328.95", "position": 0, "availableMeansEndYear": "2,395,159.54", "id": 59409650, "sectionNumber": "340"}, {"stateAgencyBalance": null, "budgetActivityEndYear": "33,350.00", "totalEndYear": "4,674,643.88", "budgetActivityBeginYear": "33,350.00", "entityClass": "ru.lanit.gmu.priv.model.document.BalanceItem", "name": "\u0443\u043c\u0435\u043d\u044c\u0448\u0435\u043d\u0438\u0435 \u0441\u0442\u043e\u0438\u043c\u043e\u0441\u0442\u0438 \u043c\u0430\u0442\u0435\u0440\u0438\u0430\u043b\u044c\u043d\u044b\u0445 \u0437\u0430\u043f\u0430\u0441\u043e\u0432", "totalBeginYear": "4,674,643.88", "incomeActivityEndYear": "3,262,267.32", "availableMeansBeginYear": "1,379,026.56", "lineCode": "362", "incomeActivityBeginYear": "3,262,267.32", "position": 0, "availableMeansEndYear": "1,379,026.56", "id": 59409651, "sectionNumber": "440"}, {"stateAgencyBalance": null, "budgetActivityEndYear": null, "totalEndYear": "0.00", "budgetActivityBeginYear": null, "entityClass": "ru.lanit.gmu.priv.model.document.BalanceItem", "name": "\u0427\u0438\u0441\u0442\u043e\u0435 \u0438\u0437\u043c\u0435\u043d\u0435\u043d\u0438\u0435 \u0437\u0430\u0442\u0440\u0430\u0442 \u043d\u0430 \u0438\u0437\u0433\u043e\u0442\u043e\u0432\u043b\u0435\u043d\u0438\u0435 \u0433\u043e\u0442\u043e\u0432\u043e\u0439 \u043f\u0440\u043e\u0434\u0443\u043a\u0446\u0438\u0438 (\u0440\u0430\u0431\u043e\u0442, \u0443\u0441\u043b\u0443\u0433)", "totalBeginYear": null, "incomeActivityEndYear": "0.00", "availableMeansBeginYear": null, "lineCode": "370", "incomeActivityBeginYear": null, "position": 0, "availableMeansEndYear": "0.00", "id": 59409652, "sectionNumber": null}, {"stateAgencyBalance": null, "budgetActivityEndYear": null, "totalEndYear": "337,036,624.33", "budgetActivityBeginYear": null, "entityClass": "ru.lanit.gmu.priv.model.document.BalanceItem", "name": "\u0443\u0432\u0435\u043b\u0438\u0447\u0435\u043d\u0438\u0435 \u0437\u0430\u0442\u0440\u0430\u0442", "totalBeginYear": "337,036,624.33", "incomeActivityEndYear": "315,248,025.90", "availableMeansBeginYear": "21,788,598.43", "lineCode": "371", "incomeActivityBeginYear": "315,248,025.90", "position": 0, "availableMeansEndYear": "21,788,598.43", "id": 59409653, "sectionNumber": "X"}, {"stateAgencyBalance": null, "budgetActivityEndYear": null, "totalEndYear": "337,036,624.33", "budgetActivityBeginYear": null, "entityClass": "ru.lanit.gmu.priv.model.document.BalanceItem", "name": "\u0443\u043c\u0435\u043d\u044c\u0448\u0435\u043d\u0438\u0435 \u0437\u0430\u0442\u0440\u0430\u0442", "totalBeginYear": "337,036,624.33", "incomeActivityEndYear": "315,248,025.90", "availableMeansBeginYear": "21,788,598.43", "lineCode": "372", "incomeActivityBeginYear": "315,248,025.90", "position": 0, "availableMeansEndYear": "21,788,598.43", "id": 59409654, "sectionNumber": "X"}], "grbsFullName": null}, "formationPeriods": [{"nextFinancialYear": 2012, "financialYear": 2012, "founderCheckPrintFormId": null, "agency": null, "stateTask": false, "publishDate": 1373029883088, "formationPeriod": 2012, "checkedByFounder": null, "id": 16119, "founderCheckResult": null}, {"nextFinancialYear": 2013, "financialYear": 2013, "founderCheckPrintFormId": null, "agency": null, "stateTask": false, "publishDate": 1401441661385, "formationPeriod": 2013, "checkedByFounder": null, "id": 215862, "founderCheckResult": null}, {"nextFinancialYear": 2014, "financialYear": 2014, "founderCheckPrintFormId": null, "agency": null, "stateTask": false, "publishDate": 1445255431547, "formationPeriod": 2014, "checkedByFounder": null, "id": 383130, "founderCheckResult": null}, {"nextFinancialYear": 2015, "financialYear": 2015, "founderCheckPrintFormId": null, "agency": null, "stateTask": false, "publishDate": 1458121543955, "formationPeriod": 2015, "checkedByFounder": null, "id": 461757, "founderCheckResult": null}], "planFactComparisonAvail": true, "checkInfoSection": "AB0503721", "activeTab": "COMMON", "agency": {"typeOfInfoResponsibilityList": null, "okoguCode": "2300223", "glavaCode": null, "oktmo": null, "specialInstruction": "05", "rbsAgencyRegNum": "0173200000105", "estateUsageReports": null, "agencyFounderLinks": null, "branchFlag": false, "hasSiteOperatorAuthority": false, "spzClientCode": "03732002757", "grbsAgencyName": "\u0412\u043e\u0441\u0442\u043e\u0447\u043d\u043e\u0435 \u043e\u043a\u0440\u0443\u0436\u043d\u043e\u0435 \u0443\u043f\u0440\u0430\u0432\u043b\u0435\u043d\u0438\u0435 \u043e\u0431\u0440\u0430\u0437\u043e\u0432\u0430\u043d\u0438\u044f \u0414\u0435\u043f\u0430\u0440\u0442\u0430\u043c\u0435\u043d\u0442\u0430 \u043e\u0431\u0440\u0430\u0437\u043e\u0432\u0430\u043d\u0438\u044f \u0433\u043e\u0440\u043e\u0434\u0430 \u041c\u043e\u0441\u043a\u0432\u044b", "importPositionChangeDate": 1454719618000, "registrationDate": 1336208769466, "hasFounderAuthority": false, "bik": null, "blockStatus": "A", "activeFromDate": 1324929600000, "ppoOkato": null, "okopf": null, "pubpClientCode": null, "kpp": "772001001", "egrulUpdateDate": 1453064400000, "representativeTofk": false, "ppoName": null, "financialAgencyRegNum": "0173200000068", "lastPublishedEntityType": "activity-estate-usage-report", "grbsAgencyRegNum": "0173200000084", "agencyCode": "0373200005375", "agencyAddress": null, "managerPosition": "\u0414\u0418\u0420\u0415\u041a\u0422\u041e\u0420", "ogrn": "5077746818452", "lastPublishedEntityId": 875101, "nomBank": null, "okvedLinks": null, "responsibleBPGMU": false, "section": "075", "egrul": false, "financialActivityPlans": null, "agencyTypeBySpecifiedPeriodList": null, "tegAgencies": [], "email": "2031@edu.mos.ru", "okpoCode": "80880239", "okato": null, "agencyRepresenterLink": null, "summaryRegistryDateInclusion": null, "lastEventDate": 1461058397549, "okogu": null, "agencyBudgets": null, "rubpClientCode": null, "tofkFlag": null, "headAgencyRegNum": "0173200000068", "hasRepresentativeAgencyAuthority": false, "ubpClientCode": "\u04206090", "enactment": null, "ppo": null, "uoRegistrationDate": null, "tofk": null, "dependedPPOforFOId": null, "generalInformationList": null, "agencyManagers": null, "controlMeasureInfoList": null, "egrulBasedUpdateDate": 1454706000000, "authAgencyUsers": null, "stateAgencyTasks": null, "okpo": null, "hasSupervisorAgencyAuthority": false, "annulment": false, "lockVersion": 107, "shortClientAltName": null, "anotherAgencyInfoList": null, "subsidized": true, "website": "http://schv2031.mskobr.ru", "registerPublicServices": null, "okfs": null, "entityClass": "ru.lanit.gmu.priv.model.catalog.Agency", "hasInstitutionAuthority": true, "founderRequest": null, "ogv": false, "tofkCode": "7304", "firmClientName": null, "fullClientName": "\u0413\u041e\u0421\u0423\u0414\u0410\u0420\u0421\u0422\u0412\u0415\u041d\u041d\u041e\u0415 \u0411\u042e\u0414\u0416\u0415\u0422\u041d\u041e\u0415 \u041e\u0411\u0429\u0415\u041e\u0411\u0420\u0410\u0417\u041e\u0412\u0410\u0422\u0415\u041b\u042c\u041d\u041e\u0415 \u0423\u0427\u0420\u0415\u0416\u0414\u0415\u041d\u0418\u0415 \u0413\u041e\u0420\u041e\u0414\u0410 \u041c\u041e\u0421\u041a\u0412\u042b \"\u0428\u041a\u041e\u041b\u0410 \u2116 2031\"", "summaryRegistryCode": null, "managerMiddleName": "\u041d\u0418\u041a\u041e\u041b\u0410\u0415\u0412\u0418\u0427", "dependedPPOforFO": null, "autorityAgencyFlag": null, "publishedGeneralInformationId": 1950800, "lastModifyDate": 1454918034094, "hasFinancialAgencyAuthority": false, "agencyLevel": "S", "businessStatusName": "801", "agencyAccountList": null, "inn": "7720584916", "rbsAgencyName": "\u0414\u0435\u043f\u0430\u0440\u0442\u0430\u043c\u0435\u043d\u0442 \u043e\u0431\u0440\u0430\u0437\u043e\u0432\u0430\u043d\u0438\u044f \u0433\u043e\u0440\u043e\u0434\u0430 \u041c\u043e\u0441\u043a\u0432\u044b", "publishedGeneralInformation": null, "id": 158081, "managerFirstName": "\u0412\u0410\u0421\u0418\u041b\u0418\u0419", "shortClientName": "\u0413\u0411\u041e\u0423 \u0428\u041a\u041e\u041b\u0410 \u2116 2031", "newBusinessStatusName": "801", "lastAgencyInformationChangeDate": 1461058397549, "managerSecondName": "\u0414\u041e\u041b\u041c\u0410\u0422\u041e\u0412", "activeToDate": null, "branch": null, "vgu": null, "authorityInfo": "\u041f\u043e\u043b\u043d\u043e\u043c\u043e\u0447\u0438\u0435 \u0443\u0447\u0440\u0435\u0436\u0434\u0435\u043d\u0438\u044f", "registered": true, "agencyType": "B", "blocks": null, "users": null, "foiv": false, "assignmentOgrnDate": null, "scopesActivities": null, "ppoOktmo": null, "branches": null, "phone": "8-499-7217281", "credentialsOos": null, "credentialsFk": null, "budgetOperationList": null}, "changesHistoryEntitySid": 461757, "feedbackFinancialYear": 2015, "founderChecked": false, "publishedInfoMap": {"hasAnnualBalanceF0503121": false, "hasAnnualBalanceF0503130": false, "hasBudgetaryCommitments": false, "hasAnnualBalanceF0503127": false, "hasAnnualBalanceF0503730": true, "hasAnnualBalanceF0503737": true, "hasStateAgencyTask": true, "hasAnnualBalanceF0503721": true, "hasAnnualBalanceF0503137": false, "hasBudgetOperation": true, "hasFinancialActivityPlans": true}, "hasPaymentTargets": false, "changesHistoryEntityType": "annual-balance-F0503721", "changesHistoryActualId": 461757, "wrongInfoFeedbackBannerEnabled": true, "feedbackAgencyId": 158081}